[
  {
    "id": 12693,
    "question": "きのう デパート___ かいものを しました。",
    "answer1": "が",
    "answer2": "に",
    "answer3": "で",
    "answer4": "へ",
    "result": "で",
    "img": "",
    "description": ""
  },
  {
    "id": 12694,
    "question": "本が 2さつ あります。ノート____ 2さつ あります。",
    "answer1": "や",
    "answer2": "も",
    "answer3": "で",
    "answer4": "に",
    "result": "も",
    "img": "",
    "description": ""
  },
  {
    "id": 12695,
    "question": "らいしゅう 京都へ りょこう____ 行きます。",
    "answer1": "と",
    "answer2": "が",
    "answer3": "を",
    "answer4": "に",
    "result": "に",
    "img": "",
    "description": ""
  },
  {
    "id": 12696,
    "question": "わたしは まいにち 日本語____ べんきょうを します。",
    "answer1": "と",
    "answer2": "の",
    "answer3": "や",
    "answer4": "を",
    "result": "の",
    "img": "",
    "description": ""
  },
  {
    "id": 12697,
    "question": "「あしたも ひとりで 来ますか。」「いいえ、あしたは ともだち ___ 来ます。」",
    "answer1": "と",
    "answer2": "は",
    "answer3": "へ",
    "answer4": "が",
    "result": "と",
    "img": "",
    "description": ""
  },
  {
    "id": 12698,
    "question": "「さようなら」は 中国語 ____ なんと いいますか。",
    "answer1": "が",
    "answer2": "を",
    "answer3": "で",
    "answer4": "に",
    "result": "で",
    "img": "",
    "description": ""
  },
  {
    "id": 12699,
    "question": "ここに なまえ____ でんわばんごうを かいて ください。",
    "answer1": "で",
    "answer2": "を",
    "answer3": "と",
    "answer4": "も",
    "result": "と",
    "img": "",
    "description": ""
  },
  {
    "id": 12700,
    "question": "わたしは いつも うちから えき___ じてんしゃで 行きます。",
    "answer1": "しか",
    "answer2": "まで",
    "answer3": "ごろ",
    "answer4": "で",
    "result": "まで",
    "img": "",
    "description": ""
  },
  {
    "id": 12701,
    "question": "この バスは びょういんの まえ____ とおります。",
    "answer1": "で",
    "answer2": "に",
    "answer3": "へ",
    "answer4": "を",
    "result": "を",
    "img": "",
    "description": ""
  },
  {
    "id": 12702,
    "question": "どれ____ あなたの かぎですか。",
    "answer1": "は",
    "answer2": "や",
    "answer3": "を",
    "answer4": "が",
    "result": "が",
    "img": "",
    "description": ""
  },
  {
    "id": 12703,
    "question": "なつやすみは なんにち____ はじまりますか。",
    "answer1": "だけ",
    "answer2": "では",
    "answer3": "から",
    "answer4": "まで",
    "result": "から",
    "img": "",
    "description": ""
  },
  {
    "id": 12704,
    "question": "しんぶんを さがしましたが、どこ____ ありません。",
    "answer1": "にも",
    "answer2": "でも",
    "answer3": "までも",
    "answer4": "へも",
    "result": "にも",
    "img": "",
    "description": ""
  },
  {
    "id": 12705,
    "question": "パーティーは なんじに はじまる ____ 知って いますか。",
    "answer1": "か",
    "answer2": "で",
    "answer3": "を",
    "answer4": "が",
    "result": "か",
    "img": "",
    "description": ""
  },
  {
    "id": 12706,
    "question": "おかねは 1000円____ あります。",
    "answer1": "ぐらい",
    "answer2": "ごろ",
    "answer3": "しか",
    "answer4": "にも",
    "result": "ぐらい",
    "img": "",
    "description": ""
  },
  {
    "id": 12707,
    "question": "かさは そこ ____ おいて ください。",
    "answer1": "と",
    "answer2": "が",
    "answer3": "を",
    "answer4": "に",
    "result": "に",
    "img": "",
    "description": ""
  },
  {
    "id": 12708,
    "question": "わたしは あまり ___ ありませんでした。",
    "answer1": "じょうぶでは",
    "answer2": "じょうぶな",
    "answer3": "じょうぶには",
    "answer4": "じょうぶだ",
    "result": "じょうぶでは",
    "img": "",
    "description": ""
  },
  {
    "id": 12709,
    "question": "わたしの へやは ____ ないです。",
    "answer1": "ひろいく",
    "answer2": "ひろいでは",
    "answer3": "ひろく",
    "answer4": "ひろい",
    "result": "ひろく",
    "img": "",
    "description": ""
  },
  {
    "id": 12710,
    "question": "あの 子は うたを ___ うたいます。",
    "answer1": "じょうず",
    "answer2": "じょうずな",
    "answer3": "じょうずに",
    "answer4": "じょうずで",
    "result": "じょうずに",
    "img": "",
    "description": ""
  },
  {
    "id": 12711,
    "question": "字を もう すこし ____ かきましょう。",
    "answer1": "大きい",
    "answer2": "大きく",
    "answer3": "大きいに",
    "answer4": "大きくに",
    "result": "大きく",
    "img": "",
    "description": ""
  },
  {
    "id": 12712,
    "question": "わたしは もっと ____ たいです。",
    "answer1": "はなし",
    "answer2": "はなす",
    "answer3": "はなした",
    "answer4": "はなします",
    "result": "はなし",
    "img": "",
    "description": ""
  },
  {
    "id": 12713,
    "question": "ここで ___ ください。",
    "answer1": "あそばない",
    "answer2": "あそばなく",
    "answer3": "あそばなくて",
    "answer4": "あそばないで",
    "result": "あそばないで",
    "img": "",
    "description": ""
  },
  {
    "id": 12714,
    "question": "わたしは きのう ____ まえに、てがみを かきました。",
    "answer1": "ねる",
    "answer2": "ねた",
    "answer3": "ねるの",
    "answer4": "ねたの",
    "result": "ねる",
    "img": "",
    "description": ""
  },
  {
    "id": 12715,
    "question": "きのう 本を____ に 行きました。",
    "answer1": "かって",
    "answer2": "かう",
    "answer3": "かわ",
    "answer4": "かい",
    "result": "かい",
    "img": "",
    "description": ""
  },
  {
    "id": 12716,
    "question": "わたしは おんがくを ___ ながら べんきょうします。",
    "answer1": "きく",
    "answer2": "きき",
    "answer3": "きいた",
    "answer4": "きいて",
    "result": "きき",
    "img": "",
    "description": ""
  },
  {
    "id": 12717,
    "question": "あした 山田さんが ___ 人は だれですか。",
    "answer1": "あって",
    "answer2": "あいます",
    "answer3": "あった",
    "answer4": "あう",
    "result": "あう",
    "img": "",
    "description": ""
  },
  {
    "id": 12718,
    "question": "「いま すぐ ビールを のみますか。」「いいえ、おふろに ___から のみま す。」",
    "answer1": "はいる",
    "answer2": "はいり",
    "answer3": "はいります",
    "answer4": "はいって",
    "result": "はいって",
    "img": "",
    "description": ""
  },
  {
    "id": 12719,
    "question": "かべに ポスターが はって___。",
    "answer1": "います",
    "answer2": "なります",
    "answer3": "あります",
    "answer4": "します",
    "result": "あります",
    "img": "",
    "description": ""
  },
  {
    "id": 12720,
    "question": "この えは わたしが きのう こうえんで ___えです。",
    "answer1": "かく",
    "answer2": "かかない",
    "answer3": "かいた",
    "answer4": "かいて",
    "result": "かいた",
    "img": "",
    "description": ""
  },
  {
    "id": 12721,
    "question": "こどもは ゆうべ ばんごはんを ____ ねました。",
    "answer1": "たべなくて",
    "answer2": "たべないで",
    "answer3": "たべない",
    "answer4": "たべなく",
    "result": "たべないで",
    "img": "",
    "description": ""
  },
  {
    "id": 12722,
    "question": "しんぶんは あまり____。",
    "answer1": "よみます",
    "answer2": "よみません",
    "answer3": "よんで",
    "answer4": "さい",
    "result": "よみません",
    "img": "",
    "description": ""
  },
  {
    "id": 12723,
    "question": "「りょこうは ___でしたか。」 「たのしかったです。」",
    "answer1": "どう",
    "answer2": "いつ",
    "answer3": "なぜ",
    "answer4": "だれ",
    "result": "どう",
    "img": "",
    "description": ""
  },
  {
    "id": 12724,
    "question": "「___ しごとを やすみましたか。」 「びょうきだったからです。」",
    "answer1": "どこの",
    "answer2": "どなたが",
    "answer3": "どうして",
    "answer4": "どのぐらい",
    "result": "どうして",
    "img": "",
    "description": ""
  },
  {
    "id": 12725,
    "question": "「それは ___ の 国の きってですか。」 「日本のです。」",
    "answer1": "なに",
    "answer2": "どれ",
    "answer3": "いつ",
    "answer4": "どこ",
    "result": "どこ",
    "img": "",
    "description": ""
  },
  {
    "id": 12726,
    "question": "「パーティーでは どんな ___を のみましたか。」 「ジュースや コーラを のみました。」",
    "answer1": "ひと",
    "answer2": "こと",
    "answer3": "もの",
    "answer4": "とき",
    "result": "もの",
    "img": "",
    "description": ""
  },
  {
    "id": 12727,
    "question": "びょうきで きょう いちにち、____ たべませんでした。",
    "answer1": "なにに",
    "answer2": "なにか",
    "answer3": "なんで",
    "answer4": "なにも",
    "result": "なにも",
    "img": "",
    "description": ""
  },
  {
    "id": 12728,
    "question": "____ ください。",
    "answer1": "りんごを3つを",
    "answer2": "りんごを3つ",
    "answer3": "りんごが3つを",
    "answer4": "りんごが3つ",
    "result": "りんごを3つ",
    "img": "",
    "description": ""
  },
  {
    "id": 12729,
    "question": "A「おにいさんは おげんきですか。」 B「____。」",
    "answer1": "はい、おかげさまで",
    "answer2": "あ、どういたしまして",
    "answer3": "いいえ、ありがとう",
    "answer4": "ええ、",
    "result": "はい、おかげさまで",
    "img": "",
    "description": ""
  },
  {
    "id": 12730,
    "question": "A「さとうさんは もう 来ましたか。」 B「____。」",
    "answer1": "いいえ、来ませんでした",
    "answer2": "いいえ、まだです",
    "answer3": "はい、そうです",
    "answer4": "はい、も",
    "result": "いいえ、まだです",
    "img": "",
    "description": ""
  },
  {
    "id": 12731,
    "question": "あ「えきから がっこうまでは とおいですか。」 B「いいえ、____。」",
    "answer1": "あるいて3ぷぶんです",
    "answer2": "あるいて3ぷんかかります",
    "answer3": "3ぷんあるきます",
    "answer4": "3ぷんあるいています",
    "result": "あるいて3ぷぶんです",
    "img": "",
    "description": ""
  },
  {
    "id": 12732,
    "question": "ですから、 ばんばって ください。知らない(イ)が はいって いますが、はじめは じしょを ひかない で ぜんぶ(ウ)ください。つぎに じしょを ひきながら もう (エ) よんで ください。いいで すか。2かい よむんですよ。」 問(1) (ア)",
    "answer1": "おもしろい",
    "answer2": "つまらない",
    "answer3": "やさしい",
    "answer4": "むずかしい",
    "result": "おもしろい",
    "img": "",
    "description": ""
  },
  {
    "id": 12733,
    "question": "ですから、 ばんばって ください。知らない(イ)が はいって いますが、はじめは じしょを ひかない で ぜんぶ(ウ)ください。つぎに じしょを ひきながら もう (エ) よんで ください。いいで すか。2かい よむんですよ。」 問(2) (イ)",
    "answer1": "本",
    "answer2": "ことば",
    "answer3": "じしょ",
    "answer4": "人",
    "result": "ことば",
    "img": "",
    "description": ""
  },
  {
    "id": 12734,
    "question": "ですから、 ばんばって ください。知らない(イ)が はいって いますが、はじめは じしょを ひかない で ぜんぶ(ウ)ください。つぎに じしょを ひきながら もう (エ) よんで ください。いいで すか。2かい よむんですよ。」 問(3) (ウ)",
    "answer1": "はなして",
    "answer2": "よんで",
    "answer3": "ひいて",
    "answer4": "はいって",
    "result": "よんで",
    "img": "",
    "description": ""
  },
  {
    "id": 12735,
    "question": "ですから、 ばんばって ください。知らない(イ)が はいって いますが、はじめは じしょを ひかない で ぜんぶ(ウ)ください。つぎに じしょを ひきながら もう (エ) よんで ください。いいで すか。2かい よむんですよ。」 問(4) (エ)",
    "answer1": "いっさつ",
    "answer2": "ひとり",
    "answer3": "いっぽん",
    "answer4": "いちど",
    "result": "いちど",
    "img": "",
    "description": ""
  },
  {
    "id": 12736,
    "question": "きのう ケーキを 10こ かった。ばんごはんの あと いもうとと ふたりで 2こずつ たべた。おいしかった。ケーキは いま いくつ ありますか。",
    "answer1": "2こ",
    "answer2": "4こ",
    "answer3": "6こ",
    "answer4": "8こ",
    "result": "6こ",
    "img": "",
    "description": ""
  },
  {
    "id": 12737,
    "question": "サングラスと いうのは ふつう なつの てんきの いい 日に かける めがねだが、 わたしは ふゆに よく つかう。日本では ふゆみ よく つよい 風が ふくからだ。この 人が サングラスを かけるのは どうしてですか。",
    "answer1": "風がつよいからです",
    "answer2": "さむいからです",
    "answer3": "てんきがいいからです",
    "answer4": "あついからです",
    "result": "風がつよいからです",
    "img": "",
    "description": ""
  },
  {
    "id": 12738,
    "question": "こんしゅうの もくよう日の パーティーに 出る 人は、まえの 日に キムさんに 60 0円 はらって ください。おかねを はらって パーティーに 来なかった 人には、つぎの 日に キムさんが はんぶん かえします。りんさんは おかねを はらいましたが、パーティーに 行きませんでした。キムさん は りんさんに いつ いくら かえしますか。",
    "answer1": "もくよう日に600円かえします。",
    "answer2": "もくよう日に300円かえします。",
    "answer3": "きんよう日に600円かえします。",
    "answer4": "きんよう日に300円かえします。",
    "result": "きんよう日に300円かえします。",
    "img": "",
    "description": ""
  }
]