[
  {
    "id": 8401,
    "question": "京都大学霊長類(注１)研究所には「アイ」という有名なチンパンジー(注２)が飼われています。研究所ではチンパンジーに言葉を覚えさせる研究をしているのですが、このアイはすでに約１００の言葉を覚えていて、１けたの数字なら５つまで同時に記憶できるそうです。最近、アイには赤ちゃんが生まれ、「アユム」という名前がつけられました。アイが覚えた言葉や知識をアユムにどう伝えるかなど、研究もさらに広がりそうで楽しみです。\n\n(注１)　霊長類：人類やサル類\n\n(注２)　チンパンジー：サル類の中で最も知能が高いサル\n\n \n\n　この文章の内容と合っているものはどれか。 ",
    "answer1": "アイは１００の言葉を同時に記憶することができる。",
    "answer2": "アイの覚えた言葉はアユムも覚えることができる。",
    "answer3": "アイは数字の３と４を同時に記憶することができる。",
    "answer4": "アイはアユムが言葉を覚えるのを楽しみにしている。",
    "result": "アイはアユムが言葉を覚えるのを楽しみにしている。",
    "img": "",
    "description": "Ở phòng nghiên cứu động vật linh trưởng Đại học Kyoto, con tinh tinh nổi tiếng tên là AI đang được nuôi.\nNghe nói, viện nghiên cứu đang nghiên cứu làm sao để con tinh tinh có thể nhớ từ vựng, con AI này trước đây đã nhớ khoảng 100 từ, và nếu là kí tự chữ số nó có thể ghi nhớ đồng thời đến 5 kí tự. \nGần đây, AI đã sinh con, và được đặt tên là Ayumu.\nLàm thế nào mà AI có thể truyền lại những chữ và tri thức mà mình nhớ được cho Ayumu, mở rộng nghiên cứu về vấn đề này cũng rất thú vị.\n\n \n\nCâu nào phù hợp với nội dung đoạn văn này?\n\n　１　Ai có thể ghi nhớ đồng thời 100 từ vựng\n　２　Từ vựng mà Ai có thể nhớ thì Ayumu cũng có thể nhớ.\n　３　Ai có thể nhớ đồng thời 3, 4 chữ số\n　４　Ai đang mong đợi việc Ayumu có thể nhớ được từ vựng.\n"
  }
]